openmmla_vision/__init__.py
openmmla_vision/bases/__init__.py
openmmla_vision/bases/synchronizer.py
openmmla_vision/bases/video_base.py
openmmla_vision/bases/visualizer.py
openmmla_vision/camera/__init__.py
openmmla_vision/camera/camera_calibrator.py
openmmla_vision/camera/camera_sync_manager.py
openmmla_vision/camera/camera_tag_detector.py
openmmla_vision/services/__init__.py
openmmla_vision/services/video_frame_analyzer.py
openmmla_vision/utils/__init__.py
openmmla_vision/utils/analyze_utils.py
openmmla_vision/utils/apriltag_utils.py
openmmla_vision/utils/args_utils.py
openmmla_vision/utils/image_utils.py
openmmla_vision/utils/influx_client.py
openmmla_vision/utils/input_utils.py
openmmla_vision/utils/logger_utils.py
openmmla_vision/utils/mqtt_client.py
openmmla_vision/utils/prompt_utils.py
openmmla_vision/utils/redis_client.py
openmmla_vision/utils/relations_utils.py
openmmla_vision/utils/server_utils.py
openmmla_vision/utils/stream_utils.py
openmmla_vision/utils/thread_utils.py
openmmla_vision/utils/transform_utils.py
openmmla_vision-0.1.0.post4.dist-info/LICENSE
openmmla_vision-0.1.0.post4.dist-info/METADATA
openmmla_vision-0.1.0.post4.dist-info/WHEEL
openmmla_vision-0.1.0.post4.dist-info/top_level.txt
openmmla_vision-0.1.0.post4.dist-info/RECORD
