Metadata-Version: 2.1
Name: openmmla-vision
Version: 0.1.0.post4
Summary: Vision module for the OpenMMLA platform.
Author-email: Zaibei Li <lizaibeim@gmail.com>
License: MIT License
Project-URL: Homepage, https://github.com/ucph-ccs/mbox-audio
Classifier: Topic :: Multimedia :: Video :: Capture
Classifier: Topic :: Education :: Computer Aided Instruction (CAI)
Classifier: Operating System :: MacOS
Classifier: Operating System :: POSIX :: Linux
Classifier: Programming Language :: Python :: 3.9
Classifier: Programming Language :: Python :: 3.10
Classifier: License :: OSI Approved :: MIT License
Requires-Python: >=3.9.0
License-File: LICENSE
Provides-Extra: all
Requires-Dist: influxdb-client==1.44.0; extra == "all"
Requires-Dist: matplotlib==3.9.2; extra == "all"
Requires-Dist: opencv-python==4.10.0.84; extra == "all"
Requires-Dist: paho-mqtt==2.1.0; extra == "all"
Requires-Dist: pandas==2.2.2; extra == "all"
Requires-Dist: pupil-apriltags==1.0.4.post10; extra == "all"
Requires-Dist: redis==5.0.7; extra == "all"
Requires-Dist: scipy==1.14.0; extra == "all"
Requires-Dist: networkx==3.3; extra == "all"
Requires-Dist: pyecharts==2.0.6; extra == "all"
Requires-Dist: numpy==1.26.4; extra == "all"
Requires-Dist: Pillow==10.4.0; extra == "all"
Requires-Dist: huggingface-hub==0.24.6; extra == "all"
Requires-Dist: flask==3.0.3; extra == "all"
Requires-Dist: openai==1.42.0; extra == "all"
Requires-Dist: vllm==0.5.4; sys_platform == "linux" and extra == "all"
Provides-Extra: base
Requires-Dist: influxdb-client==1.44.0; extra == "base"
Requires-Dist: matplotlib==3.9.2; extra == "base"
Requires-Dist: opencv-python==4.10.0.84; extra == "base"
Requires-Dist: paho-mqtt==2.1.0; extra == "base"
Requires-Dist: pandas==2.2.2; extra == "base"
Requires-Dist: pupil-apriltags==1.0.4.post10; extra == "base"
Requires-Dist: redis==5.0.7; extra == "base"
Requires-Dist: scipy==1.14.0; extra == "base"
Requires-Dist: networkx==3.3; extra == "base"
Requires-Dist: pyecharts==2.0.6; extra == "base"
Provides-Extra: server
Requires-Dist: numpy==1.26.4; extra == "server"
Requires-Dist: opencv-python==4.10.0.84; extra == "server"
Requires-Dist: Pillow==10.4.0; extra == "server"
Requires-Dist: pupil-apriltags==1.0.4.post10; extra == "server"
Requires-Dist: huggingface-hub==0.24.6; extra == "server"
Requires-Dist: flask==3.0.3; extra == "server"
Requires-Dist: openai==1.42.0; extra == "server"
Requires-Dist: vllm==0.5.4; sys_platform == "linux" and extra == "server"
